README.md
setup.py
prodcal/__init__.py
prodcal/config.py
prodcal/holidays.py
prodcal/service.py
prodcal/prodcals/__init__.py
prodcal/prodcals/by.py
prodcal/prodcals/cn.py
prodcal/prodcals/de.py
prodcal/prodcals/ee.py
prodcal/prodcals/ge.py
prodcal/prodcals/kz.py
prodcal/prodcals/prod_dict.py
prodcal/prodcals/ru.py
prodcal/prodcals/ua.py
production_calendar.egg-info/PKG-INFO
production_calendar.egg-info/SOURCES.txt
production_calendar.egg-info/dependency_links.txt
production_calendar.egg-info/top_level.txt