Metadata-Version: 1.2
Name: production-calendar
Version: 0.1b9
Summary: Given module allows to use production calendars of different countries
Home-page: https://github.com/ivanovart/prod-cal
Author: Vladimir Sidorov
Author-email: vladimir.sidorov@raziogroup.com
Maintainer: Artem Ivanov
Maintainer-email: ivart@ivart.xyz
License: Apache 2.0
Platform: UNKNOWN
Classifier: Development Status :: 4 - Beta
Classifier: Environment :: Console
Classifier: License :: Freeware
Classifier: License :: OSI Approved :: Apache Software License
Classifier: Natural Language :: English
Classifier: Programming Language :: Python :: 3.6
Classifier: Topic :: Office/Business
Classifier: Topic :: Office/Business :: Scheduling
Classifier: Topic :: Utilities
